COPYING
COPYING.LESSER
builddoc.py
ez_setup.py
setup.py
demo/hello/Hello.png
demo/hello/gamesite.xml
demo/hello/hello.py
demo/template/game.py
demo/template/gamesite.xml
docs/overview.txt
docs/graphics/BigPicture.png
docs/screenshots/HelloGame.png
docs/screenshots/SkeletalGame.png
pymage/__init__.py
pymage/config.py
pymage/joystick.py
pymage/resman.py
pymage/sound.py
pymage/sprites.py
pymage/states.py
pymage/timer.py
pymage/ui.py
pymage/vector.py
pymage/vfs.py
pymage.egg-info/PKG-INFO
pymage.egg-info/SOURCES.txt
pymage.egg-info/dependency_links.txt
pymage.egg-info/requires.txt
pymage.egg-info/top_level.txt
pymage.egg-info/zip-safe
tests/__init__.py
tests/resmantest.py
tests/timertest.py
tests/vectortest.py
tests/data/hello.ogg
tests/data/test_img.png
