Metadata-Version: 1.0
Name: pymage
Version: 0.3.0
Summary: Pygame helper package
Home-page: http://code.google.com/p/pymage/
Author: Ross Light
Author-email: rlight2@gmail.com
License: LGPL
Download-URL: http://code.google.com/p/pymage/downloads/list
Keywords: pygame SDL configuration resource
Platform: UNKNOWN
Classifier: Development Status :: 4 - Beta
Classifier: License :: OSI Approved :: GNU Library or Lesser General Public License (LGPL)
Classifier: Natural Language :: English
Classifier: Operating System :: MacOS :: MacOS X
Classifier: Operating System :: Microsoft :: Windows
Classifier: Operating System :: POSIX :: Linux
Classifier: Programming Language :: Python
Classifier: Topic :: Games/Entertainment
